svgsimplegraph/__init__.py
svgsimplegraph/base.py
svgsimplegraph/bubble_and_arrow.py
svgsimplegraph/categorical.py
svgsimplegraph/ribbon.py
svgsimplegraph/toggle.py
svgsimplegraph/utils.py
tests/__init__.py
tests/test_bubble_and_arrow.py
tests/test_categorical.py
tests/test_gist.py
tests/test_readme_examples.py
tests/test_ribbon.py
tests/test_toggle.py
svgsimplegraph-2.0.3.dist-info/LICENSE
svgsimplegraph-2.0.3.dist-info/METADATA
svgsimplegraph-2.0.3.dist-info/WHEEL
svgsimplegraph-2.0.3.dist-info/top_level.txt
svgsimplegraph-2.0.3.dist-info/RECORD
