Metadata-Version: 2.1
Name: svgsimplegraph
Version: 2.0.3
Summary: Simple SVG graphing package
Home-page: UNKNOWN
Author: Garrett M. Petersen
Author-email: garrett.m.petersen@gmail.com
License: MIT
Project-URL: Source Code, https://github.com/GarrettPetersen/svgsimplegraph
Keywords: graph,svg,base64,svg simple graph
Platform: UNKNOWN
Classifier: Development Status :: 3 - Alpha
Classifier: Intended Audience :: Developers
Classifier: License :: OSI Approved :: MIT License
Classifier: Programming Language :: Python :: 3
